polymath_schemas/__init__.py
polymath_schemas/api_requests.py
polymath_schemas/api_responses.py
polymath_schemas/auth.py
polymath_schemas/graph.py
polymath_schemas/node_work.py
polymath_schemas/utils.py
polymath_schemas-0.3.1.dist-info/METADATA
polymath_schemas-0.3.1.dist-info/WHEEL
polymath_schemas-0.3.1.dist-info/top_level.txt
polymath_schemas-0.3.1.dist-info/RECORD
