Metadata-Version: 2.4
Name: polymath-schemas
Version: 0.3.1
Summary: Schemas for Polymath python reference implementations.
Requires-Python: >=3.13
Requires-Dist: neomodel>=6.0.0
Requires-Dist: pydantic>=2.12.5
Requires-Dist: sqlmodel>=0.0.27
